[
{"yahoo": "Agriculture, Forestry, Fishing"},
{"yahoo": "Agriculture, Forestry, Fishing"},
{"yahoo": "Agriculture, Forestry, Fishing"},
{"yahoo": "Agriculture, Forestry, Fishing"},
{"yahoo": "Agriculture, Forestry, Fishing"},
{"yahoo": "Agriculture, Forestry, Fishing"},
{"yahoo": "Agriculture, Forestry, Fishing"},
{"yahoo": "Agriculture, Forestry, Fishing"},
{"yahoo": "Agriculture, Forestry, Fishing"},
{"yahoo": "Agriculture, Forestry, Fishing"},
{"yahoo": "Agriculture, Forestry, Fishing"},
{"yahoo": "Agriculture, Forestry, Fishing"},
{"yahoo": "Agriculture, Forestry, Fishing"},
{"yahoo": "Agriculture, Forestry, Fishing"},
{"yahoo": "Agriculture, Forestry, Fishing"},
{"yahoo": "Agriculture, Forestry, Fishing"},
{"yahoo": "Agriculture, Forestry, Fishing"},
{"yahoo": "Agriculture, Forestry, Fishing"},
{"yahoo": "Agriculture, Forestry, Fishing"},
{"yahoo": "Agriculture, Forestry, Fishing"},
{"yahoo": "Agriculture, Forestry, Fishing"},
{"yahoo": "Agriculture, Forestry, Fishing"},
{"yahoo": "Agriculture, Forestry, Fishing"},
{"yahoo": "Agriculture, Forestry, Fishing"},
{"yahoo": "Agriculture, Forestry, Fishing"}
]